[{"assetID":"1230001","assetName":"Engine","slug":"Engine","parentAssetID":"Vehicles","parentAssetName":"Vehicles","tagsKeys":"Engine, Car","dateCreated":"5/8/2023, 11:37:50 PM","dateModified":"5/8/2023, 11:37:50 PM","geoScopeLink":"http://localhost:3000/dashboard/assetmanagement"},{"assetID":"110011002023","assetName":"Fuel Injectors","slug":"Fuel Injectors","parentAssetID":"Fuel Injectors","parentAssetName":"Fuel Injectors","tagsKeys":"Date","dateCreated":"5/14/2023, 11:39:48 PM","dateModified":"5/14/2023, 11:39:48 PM","geoScopeLink":"http://localhost:3000/dashboard/subasset?assets=Car"},{"assetID":"110011002024","assetName":"Timing belt/chain","slug":"Timing belt/chain","parentAssetID":"Timing belt/chain","parentAssetName":"Timing belt/chain","tagsKeys":"Date","dateCreated":"5/14/2023, 11:40:39 PM","dateModified":"5/14/2023, 11:40:39 PM","geoScopeLink":"http://localhost:3000/dashboard/subasset?assets=Car"}]